cli/__init__.py
cli/env.py
cli/exceptions.py
cli/input_interface.py
cli/install.py
cli/output_interface.py
cli/progress.py
cli/py.typed
cli/run.py
cli/status.py
quinten_cli-1.1.16.dist-info/LICENSE
quinten_cli-1.1.16.dist-info/METADATA
quinten_cli-1.1.16.dist-info/WHEEL
quinten_cli-1.1.16.dist-info/entry_points.txt
quinten_cli-1.1.16.dist-info/top_level.txt
quinten_cli-1.1.16.dist-info/RECORD
